{
  "content": [
    {
      "content": null,
      "created": "2023-05-12T03:49:50.529058Z",
      "format": null,
      "last_modified": "2023-05-12T03:48:29.956621Z",
      "mimetype": null,
      "name": "simple-operations.ipynb",
      "path": "xeus-sqlite/simple-operations.ipynb",
      "size": 20453,
      "type": "notebook",
      "writable": true
    }
  ],
  "created": "2023-05-12T03:49:50.529058Z",
  "format": "json",
  "last_modified": "2023-05-12T03:49:50.529058Z",
  "mimetype": null,
  "name": "xeus-sqlite",
  "path": "xeus-sqlite",
  "size": null,
  "type": "directory",
  "writable": true
}